hivemind_websocket_protocol/__init__.py
hivemind_websocket_protocol/version.py
hivemind_websocket_protocol-0.0.3.dist-info/LICENSE.md
hivemind_websocket_protocol-0.0.3.dist-info/METADATA
hivemind_websocket_protocol-0.0.3.dist-info/WHEEL
hivemind_websocket_protocol-0.0.3.dist-info/entry_points.txt
hivemind_websocket_protocol-0.0.3.dist-info/top_level.txt
hivemind_websocket_protocol-0.0.3.dist-info/RECORD
