Metadata-Version: 2.1
Name: hivemind-websocket-protocol
Version: 0.0.3
Summary: websocket network protocol for hivemind-core
Home-page: https://github.com/JarbasHiveMind/hivemind-websocket-protocol
Author: jarbasAi
Author-email: jarbasai@mailfence.com
License: Apache-2.0
License-File: LICENSE.md
Requires-Dist: tornado
Requires-Dist: hivemind-plugin-manager
Requires-Dist: poorman-handshake>=0.1.0
Requires-Dist: pyOpenSSL
